velocity_profile/__init__.py
velocity_profile/__main__.py
velocity_profile/_version.py
velocity_profile/velocityprofile.py
velocity_profile-1.0.0.dist-info/LICENSE
velocity_profile-1.0.0.dist-info/METADATA
velocity_profile-1.0.0.dist-info/WHEEL
velocity_profile-1.0.0.dist-info/entry_points.txt
velocity_profile-1.0.0.dist-info/top_level.txt
velocity_profile-1.0.0.dist-info/RECORD
